{
	"cmake" : 
	{
		"generator" : 
		{
			"multiConfig" : false,
			"name" : "Ninja"
		},
		"paths" : 
		{
			"cmake" : "E:/software/Clion/CLion 2022.1.1/bin/cmake/win/bin/cmake.exe",
			"cpack" : "E:/software/Clion/CLion 2022.1.1/bin/cmake/win/bin/cpack.exe",
			"ctest" : "E:/software/Clion/CLion 2022.1.1/bin/cmake/win/bin/ctest.exe",
			"root" : "E:/software/Clion/CLion 2022.1.1/bin/cmake/win/share/cmake-3.22"
		},
		"version" : 
		{
			"isDirty" : false,
			"major" : 3,
			"minor" : 22,
			"patch" : 3,
			"string" : "3.22.3",
			"suffix" : ""
		}
	},
	"objects" : 
	[
		{
			"jsonFile" : "codemodel-v2-ce97547dc3cc4c4a680f.json",
			"kind" : "codemodel",
			"version" : 
			{
				"major" : 2,
				"minor" : 3
			}
		},
		{
			"jsonFile" : "cache-v2-c86a9800fbdc41295ceb.json",
			"kind" : "cache",
			"version" : 
			{
				"major" : 2,
				"minor" : 0
			}
		},
		{
			"jsonFile" : "cmakeFiles-v1-563a3bad77a6e17c3520.json",
			"kind" : "cmakeFiles",
			"version" : 
			{
				"major" : 1,
				"minor" : 0
			}
		},
		{
			"jsonFile" : "toolchains-v1-efb11e6fefb2670ee8e0.json",
			"kind" : "toolchains",
			"version" : 
			{
				"major" : 1,
				"minor" : 0
			}
		}
	],
	"reply" : 
	{
		"cache-v2" : 
		{
			"jsonFile" : "cache-v2-c86a9800fbdc41295ceb.json",
			"kind" : "cache",
			"version" : 
			{
				"major" : 2,
				"minor" : 0
			}
		},
		"cmakeFiles-v1" : 
		{
			"jsonFile" : "cmakeFiles-v1-563a3bad77a6e17c3520.json",
			"kind" : "cmakeFiles",
			"version" : 
			{
				"major" : 1,
				"minor" : 0
			}
		},
		"codemodel-v2" : 
		{
			"jsonFile" : "codemodel-v2-ce97547dc3cc4c4a680f.json",
			"kind" : "codemodel",
			"version" : 
			{
				"major" : 2,
				"minor" : 3
			}
		},
		"toolchains-v1" : 
		{
			"jsonFile" : "toolchains-v1-efb11e6fefb2670ee8e0.json",
			"kind" : "toolchains",
			"version" : 
			{
				"major" : 1,
				"minor" : 0
			}
		}
	}
}
